qmctorch/__init__.py
qmctorch/__version__.py
qmctorch/ase/__init__.py
qmctorch/ase/ase.py
qmctorch/ase/optimizer/__init__.py
qmctorch/ase/optimizer/torch_optim.py
qmctorch/sampler/__init__.py
qmctorch/sampler/generalized_metropolis.py
qmctorch/sampler/hamiltonian.py
qmctorch/sampler/metropolis.py
qmctorch/sampler/metropolis_hasting.py
qmctorch/sampler/pints_sampler.py
qmctorch/sampler/sampler_base.py
qmctorch/sampler/symmetry.py
qmctorch/sampler/walkers.py
qmctorch/scf/__init__.py
qmctorch/scf/molecule.py
qmctorch/scf/calculator/__init__.py
qmctorch/scf/calculator/adf.py
qmctorch/scf/calculator/calculator_base.py
qmctorch/scf/calculator/pyscf.py
qmctorch/solver/__init__.py
qmctorch/solver/loss.py
qmctorch/solver/solver.py
qmctorch/solver/solver_base.py
qmctorch/utils/__init__.py
qmctorch/utils/algebra_utils.py
qmctorch/utils/constants.py
qmctorch/utils/hdf5_utils.py
qmctorch/utils/interpolate.py
qmctorch/utils/plot_data.py
qmctorch/utils/provenance.py
qmctorch/utils/stat_utils.py
qmctorch/utils/torch_utils.py
qmctorch/wavefunction/__init__.py
qmctorch/wavefunction/slater_jastrow.py
qmctorch/wavefunction/wf_base.py
qmctorch/wavefunction/jastrows/__init__.py
qmctorch/wavefunction/jastrows/combine_jastrow.py
qmctorch/wavefunction/jastrows/distance/__init__.py
qmctorch/wavefunction/jastrows/distance/electron_electron_distance.py
qmctorch/wavefunction/jastrows/distance/electron_nuclei_distance.py
qmctorch/wavefunction/jastrows/distance/scaling.py
qmctorch/wavefunction/jastrows/elec_elec/__init__.py
qmctorch/wavefunction/jastrows/elec_elec/jastrow_factor_electron_electron.py
qmctorch/wavefunction/jastrows/elec_elec/kernels/__init__.py
qmctorch/wavefunction/jastrows/elec_elec/kernels/double_fully_connected_jastrow_kernel.py
qmctorch/wavefunction/jastrows/elec_elec/kernels/fully_connected_jastrow_kernel.py
qmctorch/wavefunction/jastrows/elec_elec/kernels/jastrow_kernel_electron_electron_base.py
qmctorch/wavefunction/jastrows/elec_elec/kernels/pade_jastrow_kernel.py
qmctorch-0.4.0.dist-info/LICENSE
qmctorch-0.4.0.dist-info/METADATA
qmctorch-0.4.0.dist-info/NOTICE
qmctorch-0.4.0.dist-info/WHEEL
qmctorch-0.4.0.dist-info/top_level.txt
qmctorch-0.4.0.dist-info/RECORD
