Metadata-Version: 2.1
Name: qmctorch
Version: 0.4.0
Summary: Pytorch Implementation of Quantum Monte Carlo
Home-page: https://github.com/NLESC-JCER/QMCTorch
Author: ['Nicolas Renaud', 'Felipe Zapata']
Author-email: n.renaud@esciencecenter.nl
License: Apache Software License 2.0
Keywords: qmctorch
Classifier: Development Status :: 4 - Beta
Classifier: Intended Audience :: Science/Research
Classifier: License :: OSI Approved :: Apache Software License
Classifier: Natural Language :: English
Classifier: Programming Language :: Python :: 3.9
Classifier: Topic :: Scientific/Engineering :: Chemistry
License-File: LICENSE
License-File: NOTICE
Requires-Dist: matplotlib
Requires-Dist: numpy
Requires-Dist: argparse
Requires-Dist: scipy
Requires-Dist: tqdm
Requires-Dist: torch
Requires-Dist: h5py
Requires-Dist: pints
Requires-Dist: mendeleev
Requires-Dist: twiggy
Requires-Dist: plams
Requires-Dist: ase
Requires-Dist: pyscf; platform_system != "Windows"
Provides-Extra: doc
Requires-Dist: recommonmark; extra == "doc"
Requires-Dist: sphinx; extra == "doc"
Requires-Dist: sphinx-rtd-theme; extra == "doc"
Requires-Dist: nbsphinx; extra == "doc"
Requires-Dist: nbconvert; extra == "doc"
Requires-Dist: jupyter; extra == "doc"
Provides-Extra: test
Requires-Dist: pytest; extra == "test"
Requires-Dist: pytest-runner; extra == "test"
Requires-Dist: coverage; extra == "test"
Requires-Dist: coveralls; extra == "test"
Requires-Dist: pycodestyle; extra == "test"
